behavior_eval/__init__.py
behavior_eval/global_config.yaml
behavior_eval/main.py
behavior_eval/data/demo_names.json
behavior_eval/data/demo_stats.json
behavior_eval/evaluation/__init__.py
behavior_eval/evaluation/action_sequence/__init__.py
behavior_eval/evaluation/action_sequence/action_sequence_evaluator.py
behavior_eval/evaluation/action_sequence/resources/__init__.py
behavior_eval/evaluation/action_sequence/resources/human_annotations/assembling_gift_baskets_0_Beechwood_0_int_0_2021-10-26_12-46-37.json
behavior_eval/evaluation/action_sequence/resources/human_annotations/bottling_fruit_0_Wainscott_0_int_0_2021-05-24_19-46-46.json
behavior_eval/evaluation/action_sequence/resources/human_annotations/boxing_books_up_for_storage_0_Benevolence_1_int_0_2021-09-10_15-35-47.json
behavior_eval/evaluation/action_sequence/resources/human_annotations/bringing_in_wood_0_Benevolence_1_int_0_2021-09-15_18-42-25.json
behavior_eval/evaluation/action_sequence/resources/human_annotations/brushing_lint_off_clothing_0_Pomaria_2_int_0_2021-06-04_17-41-56.json
behavior_eval/evaluation/action_sequence/resources/human_annotations/chopping_vegetables_0_Rs_int_0_2021-05-25_22-01-16.json
behavior_eval/evaluation/action_sequence/resources/human_annotations/cleaning_a_car_0_Ihlen_0_int_0_2021-09-11_16-37-11.json
behavior_eval/evaluation/action_sequence/resources/human_annotations/cleaning_barbecue_grill_0_Ihlen_0_int_0_2021-09-10_16-02-39.json
behavior_eval/evaluation/action_sequence/resources/human_annotations/cleaning_bathrooms_0_Benevolence_0_int_1_2021-06-12_19-33-28.json
behavior_eval/evaluation/action_sequence/resources/human_annotations/cleaning_bathtub_0_Pomaria_0_int_0_2021-09-10_16-22-10.json
behavior_eval/evaluation/action_sequence/resources/human_annotations/cleaning_bedroom_0_Benevolence_2_int_0_2021-06-06_18-10-59.json
behavior_eval/evaluation/action_sequence/resources/human_annotations/cleaning_carpets_0_Wainscott_1_int_0_2021-09-11_01-12-41.json
behavior_eval-1.0.7.dist-info/LICENSE
behavior_eval-1.0.7.dist-info/METADATA
behavior_eval-1.0.7.dist-info/WHEEL
behavior_eval-1.0.7.dist-info/top_level.txt
behavior_eval-1.0.7.dist-info/RECORD
