Metadata-Version: 2.1
Name: behavior-eval
Version: 1.0.7
Home-page: https://github.com/embodied-agent-eval/behavior-eval
Author: stanford
Requires-Python: >=3.8
License-File: LICENSE
Requires-Dist: fire
Requires-Dist: lark
Requires-Dist: bddl-eval
Requires-Dist: pyquaternion
